Zoomba/APILibrary.py
Zoomba/DesktopLibrary.py
Zoomba/GUILibrary.py
Zoomba/MobileLibrary.py
Zoomba/SOAPLibrary.py
Zoomba/ZoombaError.py
Zoomba/__init__.py
Zoomba/Helpers/ReactSelect.py
Zoomba/Helpers/__init__.py
robotframework_zoomba-4.5.0.dist-info/LICENSE
robotframework_zoomba-4.5.0.dist-info/METADATA
robotframework_zoomba-4.5.0.dist-info/WHEEL
robotframework_zoomba-4.5.0.dist-info/top_level.txt
robotframework_zoomba-4.5.0.dist-info/RECORD
