Metadata-Version: 2.1
Name: robotframework-zoomba
Version: 4.5.0
Summary: Robot Framework mini-framework.
Home-page: https://github.com/Accruent/zoomba
Maintainer: Alex Calandra, Michael Hintz, Keith Smoland, Matthew Giardina, Brandon Wolfe, Neil Howell, Tommy Hoang
Maintainer-email: robosquad@accruent.com
License: GPL-3.0
Keywords: Robot Framework robot-framework selenium requests appium soap winappdriver appium robotframeworkdesktop windows zoomba python robotframework-library appium-windows appiumlibrary api-rest api soap-api appium-mobile mobile
Platform: any
Classifier: Development Status :: 5 - Production/Stable
Classifier: Operating System :: OS Independent
Classifier: Programming Language :: Python :: 3
Classifier: Topic :: Software Development :: Testing
Classifier: Framework :: Robot Framework :: Library
License-File: LICENSE
Requires-Dist: robotframework ==7.4
Requires-Dist: robotframework-requests ==0.9.7
Requires-Dist: robotframework-seleniumlibrary ==6.8.0
Requires-Dist: robotframework-sudslibrary-aljcalandra ==1.1.4
Requires-Dist: requests ==2.32.5
Requires-Dist: selenium ==4.39.0
Requires-Dist: python-dateutil >=2.8.2
Requires-Dist: pandas >=1.3.5
Requires-Dist: zipp >=3.19.1
Provides-Extra: testing
Requires-Dist: mock ; extra == 'testing'
